wildcode/__init__.py
wildcode/_version.py
wildcode/evaluate.py
wildcode/generate.py
wildcode/inspect.py
wildcode/lecacy_sanitize.py
wildcode/model.py
wildcode/sanitize.py
wildcode/syncheck.py
wildcode/data/__init__.py
wildcode/data/utils.py
wildcode/data/wildcodebench.py
wildcode/eval/__init__.py
wildcode/eval/_special_oracle.py
wildcode/eval/utils.py
wildcode/gen/__init__.py
wildcode/gen/util/__init__.py
wildcode/gen/util/anthropic_request.py
wildcode/gen/util/openai_request.py
wild_code-0.5.1.dist-info/LICENSE
wild_code-0.5.1.dist-info/METADATA
wild_code-0.5.1.dist-info/WHEEL
wild_code-0.5.1.dist-info/entry_points.txt
wild_code-0.5.1.dist-info/top_level.txt
wild_code-0.5.1.dist-info/RECORD
