Metadata-Version: 2.1
Name: wild-code
Version: 0.5.1
Summary: "WildCode: A minimal viable package to evaluate code generation with realistic constraints in the wild"
Home-page: https://github.com/bigcode-project/wild-code
License: Apache-2.0
Platform: any
Classifier: Operating System :: OS Independent
Classifier: Programming Language :: Python :: 3
Classifier: License :: OSI Approved :: Apache Software License
Requires-Python: >=3.8
License-File: LICENSE
Requires-Dist: wget >=3.2
Requires-Dist: tempdir >=0.7.1
Requires-Dist: multipledispatch >=0.6.0
Requires-Dist: appdirs >=1.4.4
Requires-Dist: numpy >=1.19.5
Requires-Dist: tqdm >=4.56.0
Requires-Dist: termcolor >=2.0.0
Requires-Dist: fire >=0.6.0
Requires-Dist: openai >=1.11.1
Requires-Dist: rich >=12.3.0
Requires-Dist: tree-sitter-languages >=1.10.2
Requires-Dist: tree-sitter ==0.21.3
Requires-Dist: Pympler >=1.0.1
Requires-Dist: accelerate
Requires-Dist: vllm
Requires-Dist: anthropic
Requires-Dist: mistralai
Requires-Dist: stop-sequencer
Requires-Dist: google-generativeai
